C_healthy/C_healthy.py
C_healthy/__init__.py
C_healthy/test_C_healthy.py
c_healthy-0.2.6.dist-info/licenses/LICENSE
c_healthy-0.2.6.dist-info/METADATA
c_healthy-0.2.6.dist-info/WHEEL
c_healthy-0.2.6.dist-info/top_level.txt
c_healthy-0.2.6.dist-info/RECORD
