Metadata-Version: 2.4
Name: C_healthy
Version: 0.2.6
Summary: A library for calculating body index and and give advice
Home-page: https://github.com/trgchinhh/LibraryChealthy
Author: Nguyen Truong Chinh
Author-email: chinhcuber@gmail.com
Keywords: BMI,BMR,TDEE,INSTRUCT,WHR,LBM,BFP,BBW,IBW,MA,FFMI,RFM,VFR,BSA,VO2MAX,HSI,MMI,BFM,NABMI,NABMR,NATDEE,NAWHR,NALBM,NABFP,NABBW,NAIBW,NAMA,NAFFMI,NARFM,NAVFR,NABSA,NAVO2MAX,NAHSI,NAMMI,NABFM
Classifier: Programming Language :: Python :: 3
Classifier: License :: OSI Approved :: MIT License
Classifier: Operating System :: OS Independent
Requires-Python: >=3.6
License-File: LICENSE
Dynamic: author
Dynamic: author-email
Dynamic: classifier
Dynamic: description
Dynamic: description-content-type
Dynamic: home-page
Dynamic: keywords
Dynamic: license-file
Dynamic: requires-python
Dynamic: summary
